{
  "id": "grand-theft-auto-vi",
  "title": "Grand Theft Auto VI",
  "slug": "grand-theft-auto-vi",
  "short_description": "The highly anticipated next instalment in the Grand Theft Auto series.",
  "description": "Grand Theft Auto VI is the upcoming entry in Rockstar Games' flagship open-world franchise. Set in the fictional state of Leonida, home to the neon-soaked Vice City, the game follows the story of Lucia and her partner in a sprawling criminal underworld. First revealed in December 2023, GTA VI represents the next generation of open-world gaming and is among the most anticipated titles in video game history.",
  "release_date": "2025-10-01",
  "status": "in_development",
  "companies": {
    "developer": ["rockstar-north"],
    "publishers": ["rockstar-games"],
    "service_companies": [],
    "used_tooling": [],
    "supported_by": []
  },
  "genres": ["action", "open-world", "adventure"],
  "platforms": ["ps5", "xbox-series-xs"],
  "cover_image": "",
  "screenshots": [],
  "video": { "type": "youtube", "id": "QdBZY2fkU-0" },
  "stores": {},
  "play_now": {},
  "physical_stores": {},
  "critic_ratings": {},
  "database_links": { "igdb": "grand-theft-auto-vi" },
  "awards": [],
  "news": [],
  "is_student_game": false
}
