{
  "id": "alpha-revolver-games",
  "name": "Alpha Revolver Games",
  "slug": "alpha-revolver-games",
  "categories": [
    "developer"
  ],
  "status": "defunct",
  "founded": 2013,
  "location": "Glasgow",
  "region": "glasgow-strathclyde",
  "website": "https://alpharevolvergames.wordpress.com/",
  "icon": "/images/companies/alpha-revolver-games/icon.webp",
  "logo_bg": "light",
  "highlighted": false,
  "company_size": "2-10",
  "employee_count": 2,
  "contact_email": "alpharevolvergames@hotmail.com",
  "links": {
    "twitter": "https://x.com/arevolvergames",
    "youtube": "https://www.youtube.com/channel/UCHLjHtwPthJPHcXVeiO9X-g",
    "facebook": "https://www.facebook.com/people/Alpha-Revolver-Games/100044632577255/"
  },
  "use_tooling": [],
  "employee_stats": {},
  "key_people": [],
  "awards": [],
  "news": []
}
