{
  "id": "ping-creates",
  "name": "Ping Creates",
  "slug": "ping-creates",
  "categories": [
    "developer",
    "service_provider"
  ],
  "status": "active",
  "founded": 2010,
  "previously_known_as": [],
  "location": "Stirling",
  "region": "stirling-central",
  "website": "https://pingcreates.com",
  "short_description": "Since 2010, Ping Creates has been connecting clients with audiences and customers through inspiring animation, dynamic websites, captivating games and innovative apps",
  "about": "Since 2010, Ping Creates has been connecting clients with audiences and customers through inspiring animation, dynamic websites, captivating games and innovative apps.",
  "contact_email": "hello@pingcreates.com",
  "logo": null,
  "highlighted": false,
  "parent_entity": null,
  "company_size": "2-10",
  "links": {
    "twitter": "pingcreates",
    "youtube": "@PingCreates",
    "linkedin": "pingcreates"
  },
  "use_tooling": [],
  "key_people": [],
  "employee_stats": {},
  "awards": [],
  "news": [],
  "icon": "/images/companies/ping-creates/icon.jpg"
}
